{
  "name": "VHSYS-health",
  "nodes": [
    {
      "parameters": {},
      "id": "7a18e4ee-7123-4741-be79-2493317ef63c",
      "name": "When called by another workflow",
      "type": "n8n-nodes-base.executeWorkflowTrigger",
      "typeVersion": 1,
      "position": [
        -32,
        -80
      ]
    },
    {
      "parameters": {
        "jsCode": "// ─────────────────────────────────────────────\n// VHSYS :: health\n// Rota   : GET /health\n// Fase 2 : Núcleo de status e controle\n// ─────────────────────────────────────────────\n// Sem efeitos no banco. Retorna liveness do n8n.\n\nconst now = new Date().toISOString();\n\nconsole.log(JSON.stringify({\n  timestamp: now,\n  route: 'health',\n  method: 'GET',\n  event: 'health_check',\n  level: 'info'\n}));\n\nreturn {\n  statusCode: 200,\n  body: {\n    status: 'ok',\n    service: 'VHSYS Extension Router',\n    version: 'v1',\n    timestamp: now\n  }\n};"
      },
      "type": "n8n-nodes-base.code",
      "typeVersion": 2,
      "position": [
        192,
        -80
      ],
      "id": "331f8ddd-8aaf-4fe3-b8f5-4fef12f0ba87",
      "name": "Build Health Response"
    }
  ],
  "pinData": {},
  "connections": {
    "When called by another workflow": {
      "main": [
        [
          {
            "node": "Build Health Response",
            "type": "main",
            "index": 0
          }
        ]
      ]
    }
  },
  "active": true,
  "settings": {
    "executionOrder": "v1",
    "binaryMode": "separate",
    "availableInMCP": false
  },
  "versionId": "0ed393c5-8a40-4c8b-9c11-c0cc6777e0f8",
  "meta": {
    "instanceId": "175ab660dd3bf17d65cf916e76a2ea001cc6c2fa4fe3df8877aac583db87767c"
  },
  "id": "sjWsEoIsUa8qrPcp",
  "tags": []
}